sceptre/__init__.py
sceptre/cli/__init__.py
sceptre/cli/create.py
sceptre/cli/delete.py
sceptre/cli/describe.py
sceptre/cli/diff.py
sceptre/cli/drift.py
sceptre/cli/dump.py
sceptre/cli/execute.py
sceptre/cli/helpers.py
sceptre/cli/launch.py
sceptre/cli/list.py
sceptre/cli/new.py
sceptre/cli/policy.py
sceptre/cli/prune.py
sceptre/cli/status.py
sceptre/cli/template.py
sceptre/cli/update.py
sceptre/config/__init__.py
sceptre/config/graph.py
sceptre/config/reader.py
sceptre/config/strategies.py
sceptre/connection_manager.py
sceptre/context.py
sceptre/diffing/__init__.py
sceptre/diffing/diff_writer.py
sceptre/diffing/stack_differ.py
sceptre/exceptions.py
sceptre/helpers.py
sceptre/hooks/__init__.py
sceptre/hooks/asg_scaling_processes.py
sceptre/hooks/cmd.py
sceptre/logging.py
sceptre/plan/__init__.py
sceptre/plan/actions.py
sceptre/plan/executor.py
sceptre/plan/plan.py
sceptre/resolvers/__init__.py
sceptre/resolvers/environment_variable.py
sceptre/resolvers/file_contents.py
sceptre/resolvers/join.py
sceptre/resolvers/no_value.py
sceptre/resolvers/placeholders.py
sceptre/resolvers/select.py
sceptre/resolvers/split.py
sceptre/resolvers/stack_attr.py
sceptre/resolvers/stack_output.py
sceptre/resolvers/sub.py
sceptre/stack.py
sceptre/stack_policies/lock.json
sceptre/stack_policies/unlock.json
sceptre/stack_status.py
sceptre/stack_status_colourer.py
sceptre/template.py
sceptre/template_handlers/__init__.py
sceptre/template_handlers/file.py
sceptre/template_handlers/helper.py
sceptre/template_handlers/http.py
sceptre/template_handlers/s3.py
sceptre-4.5.3.dist-info/LICENSE
sceptre-4.5.3.dist-info/METADATA
sceptre-4.5.3.dist-info/NOTICE
sceptre-4.5.3.dist-info/WHEEL
sceptre-4.5.3.dist-info/entry_points.txt
sceptre-4.5.3.dist-info/RECORD
