Metadata-Version: 2.3
Name: sceptre
Version: 4.5.3
Summary: An AWS Cloud Provisioning Tool
License: Apache-2.0
Keywords: aws,cloud,devops,infrastructure,tools,cli
Author: Sceptre
Author-email: sceptreorg@gmail.com
Requires-Python: >=3.9,<4.0
Classifier: Development Status :: 5 - Production/Stable
Classifier: Environment :: Console
Classifier: Intended Audience :: Developers
Classifier: License :: OSI Approved :: Apache Software License
Classifier: Natural Language :: English
Classifier: Programming Language :: Python :: 3
Classifier: Programming Language :: Python :: 3.9
Classifier: Programming Language :: Python :: 3.10
Classifier: Programming Language :: Python :: 3.11
Classifier: Programming Language :: Python :: 3.12
Classifier: Programming Language :: Python :: 3.13
Provides-Extra: docs
Provides-Extra: troposphere
Requires-Dist: boto3 (>=1.20.27,<2.0.0)
Requires-Dist: cfn-flip (>=1.2.3,<2.0.0)
Requires-Dist: click (>=7.0,<9.0)
Requires-Dist: colorama (>=0.2.5,<0.4.4)
Requires-Dist: deepdiff (>=8.0,<9.0)
Requires-Dist: deprecation (>=2.0,<3.0)
Requires-Dist: docutils (<0.17) ; extra == "docs"
Requires-Dist: jinja2 (>=3.0,<4.0)
Requires-Dist: jsonschema (>=3.2,<3.3)
Requires-Dist: networkx (>=2.6,<2.7)
Requires-Dist: packaging (>=16.8,<25.0)
Requires-Dist: pyyaml (>=6.0,<7.0)
Requires-Dist: sceptre-cmd-resolver (>=2.0,<3.0)
Requires-Dist: sceptre-file-resolver (>=1.0,<2.0)
Requires-Dist: sphinx (>=1.6.5,<=5.1.1) ; extra == "docs"
Requires-Dist: sphinx-autodoc-typehints (==1.19.2) ; extra == "docs"
Requires-Dist: sphinx-click (>=2.0.1,<4.0.0) ; extra == "docs"
Requires-Dist: sphinx-rtd-theme (==0.5.2) ; extra == "docs"
Requires-Dist: troposphere (>=4,<5) ; extra == "troposphere"
Project-URL: Documentation, https://docs.sceptre-project.org
Project-URL: Homepage, https://github.com/Sceptre/sceptre
Project-URL: Repository, https://github.com/Sceptre/sceptre
